miracle/__init__.py
miracle/load_model.py
miracle/Custom/EnhancedVoyageAIEmbeddings.py
miracle/Custom/__init__.py
miracle_helper-0.0.32.dist-info/METADATA
miracle_helper-0.0.32.dist-info/WHEEL
miracle_helper-0.0.32.dist-info/top_level.txt
miracle_helper-0.0.32.dist-info/RECORD
