Metadata-Version: 2.1
Name: miracle-helper
Version: 0.0.32
Summary: MIRACLE.cowf LangChain Helper
Home-page: https://github.com/MIRACLE-cowf/Powerful-Auto-Researcher.git
Author: MIRACLE.cowf
Author-email: miracle.cowf@gmail.com
Keywords: miracle,miracle.cowf,custom langchain,langchain helper,pypi
Classifier: Programming Language :: Python :: 3.6
Classifier: Programming Language :: Python :: 3.7
Classifier: Programming Language :: Python :: 3.8
Classifier: Programming Language :: Python :: 3.9
Requires-Python: >=3.10
Requires-Dist: langchain>=0.3.21
Requires-Dist: langchain-core>=0.3.48
Requires-Dist: langchain-anthropic>=0.3.10
Requires-Dist: langchain-openai>=0.3.10
Requires-Dist: langchain-core>=0.3.47
Requires-Dist: langchain-voyageai>=0.1.4
Requires-Dist: langgraph>=0.3.20
Requires-Dist: async-timeout==4.0.3
Requires-Dist: pydantic==2.10.6
Requires-Dist: pydantic-core==2.27.2
